[
  {
    "id": 1,
    "company_name": "Openledger",
    "portfolio": "ICO OpenLedger"
  },
  {
    "id": 2,
    "company_name": "BlockVC",
    "portfolio": "Qtum"
  },
  {
    "id": 3,
    "company_name": "BlockVC",
    "portfolio": "Gifto"
  },
  {
    "id": 4,
    "company_name": "BlockVC",
    "portfolio": "VeChain"
  },
  {
    "id": 5,
    "company_name": "BlockVC",
    "portfolio": "CoinMeet"
  },
  {
    "id": 6,
    "company_name": "BlockVC",
    "portfolio": "Medicalchain"
  },
  {
    "id": 7,
    "company_name": "BlockVC",
    "portfolio": "Penta"
  },
  {
    "id": 8,
    "company_name": "BlockVC",
    "portfolio": "Odyssey"
  },
  {
    "id": 9,
    "company_name": "BlockVC",
    "portfolio": "ContentBox"
  },
  {
    "id": 10,
    "company_name": "BlockVC",
    "portfolio": "Scry.info"
  },
  {
    "id": 11,
    "company_name": "BlockVC",
    "portfolio": "Ontology"
  },
  {
    "id": 12,
    "company_name": "BlockVC",
    "portfolio": "Aergo"
  },
  {
    "id": 13,
    "company_name": "BlockVC",
    "portfolio": "COVA"
  },
  {
    "id": 14,
    "company_name": "BlockVC",
    "portfolio": "IOV"
  },
  {
    "id": 15,
    "company_name": "BlockVC",
    "portfolio": "Cred"
  },
  {
    "id": 16,
    "company_name": "BlockVC",
    "portfolio": "DxChain Token"
  },
  {
    "id": 17,
    "company_name": "BlockVC",
    "portfolio": "Fantom"
  },
  {
    "id": 18,
    "company_name": "BlockVC",
    "portfolio": "Ren"
  },
  {
    "id": 19,
    "company_name": "BlockVC",
    "portfolio": "Origin Protocol"
  },
  {
    "id": 20,
    "company_name": "BlockVC",
    "portfolio": "Trust Platform"
  },
  {
    "id": 21,
    "company_name": "BlockVC",
    "portfolio": "IoTeX"
  },
  {
    "id": 22,
    "company_name": "BlockVC",
    "portfolio": "Skrumble Network"
  },
  {
    "id": 23,
    "company_name": "BlockVC",
    "portfolio": "GSENetwork"
  },
  {
    "id": 24,
    "company_name": "BlockVC",
    "portfolio": "HitChain"
  },
  {
    "id": 25,
    "company_name": "BlockVC",
    "portfolio": "NKN"
  },
  {
    "id": 26,
    "company_name": "BlockVC",
    "portfolio": "QuarkChain"
  },
  {
    "id": 27,
    "company_name": "Node Capital",
    "portfolio": "Scry.info"
  },
  {
    "id": 28,
    "company_name": "Node Capital",
    "portfolio": "QunQun"
  },
  {
    "id": 29,
    "company_name": "Node Capital",
    "portfolio": "Genaro Network"
  },
  {
    "id": 30,
    "company_name": "Node Capital",
    "portfolio": "aelf"
  },
  {
    "id": 31,
    "company_name": "Node Capital",
    "portfolio": "Gifto"
  },
  {
    "id": 32,
    "company_name": "Blockchain Capital",
    "portfolio": "0x"
  },
  {
    "id": 33,
    "company_name": "Blockchain Capital",
    "portfolio": "XRP"
  },
  {
    "id": 34,
    "company_name": "Blockchain Capital",
    "portfolio": "Stacks"
  },
  {
    "id": 35,
    "company_name": "Andreessen Horowitz",
    "portfolio": "Maker"
  },
  {
    "id": 36,
    "company_name": "Andreessen Horowitz",
    "portfolio": "Internet Computer [IOU]"
  },
  {
    "id": 37,
    "company_name": "Pantera Capital",
    "portfolio": "Zcash"
  },
  {
    "id": 38,
    "company_name": "Pantera Capital",
    "portfolio": "WAX"
  },
  {
    "id": 39,
    "company_name": "Pantera Capital",
    "portfolio": "XRP"
  },
  {
    "id": 40,
    "company_name": "Pantera Capital",
    "portfolio": "Origin Protocol"
  },
  {
    "id": 41,
    "company_name": "Pantera Capital",
    "portfolio": "Kyber Network"
  },
  {
    "id": 42,
    "company_name": "Pantera Capital",
    "portfolio": "ICON"
  },
  {
    "id": 43,
    "company_name": "Pantera Capital",
    "portfolio": "Gifto"
  },
  {
    "id": 44,
    "company_name": "Pantera Capital",
    "portfolio": "Gems"
  },
  {
    "id": 45,
    "company_name": "Pantera Capital",
    "portfolio": "FunFair"
  },
  {
    "id": 46,
    "company_name": "Pantera Capital",
    "portfolio": "Filecoin"
  },
  {
    "id": 47,
    "company_name": "Pantera Capital",
    "portfolio": "Ethereum"
  },
  {
    "id": 48,
    "company_name": "Pantera Capital",
    "portfolio": "Codex Protocol"
  },
  {
    "id": 49,
    "company_name": "Pantera Capital",
    "portfolio": "0x"
  },
  {
    "id": 50,
    "company_name": "Digital Currency Group",
    "portfolio": "Stacks"
  },
  {
    "id": 51,
    "company_name": "Digital Currency Group",
    "portfolio": "Zcash"
  },
  {
    "id": 52,
    "company_name": "Digital Currency Group",
    "portfolio": "XRP"
  },
  {
    "id": 53,
    "company_name": "Digital Currency Group",
    "portfolio": "Colu Local Network"
  },
  {
    "id": 54,
    "company_name": "Reflective Ventures",
    "portfolio": "Swytch Energy Token"
  },
  {
    "id": 55,
    "company_name": "Reflective Ventures",
    "portfolio": "Open Platform"
  },
  {
    "id": 56,
    "company_name": "Reflective Ventures",
    "portfolio": "RChain"
  },
  {
    "id": 57,
    "company_name": "Arrington XRP Capital",
    "portfolio": "Cortex"
  },
  {
    "id": 58,
    "company_name": "Arrington XRP Capital",
    "portfolio": "Hifi Finance"
  },
  {
    "id": 59,
    "company_name": "Arrington XRP Capital",
    "portfolio": "Gems"
  },
  {
    "id": 60,
    "company_name": "Arrington XRP Capital",
    "portfolio": "Nexo"
  },
  {
    "id": 61,
    "company_name": "Arrington XRP Capital",
    "portfolio": "aelf"
  },
  {
    "id": 62,
    "company_name": "Arrington XRP Capital",
    "portfolio": "Stacks"
  },
  {
    "id": 63,
    "company_name": "Arrington XRP Capital",
    "portfolio": "Bloom"
  },
  {
    "id": 64,
    "company_name": "Arrington XRP Capital",
    "portfolio": "Propy"
  },
  {
    "id": 65,
    "company_name": "Arrington XRP Capital",
    "portfolio": "XRP"
  },
  {
    "id": 66,
    "company_name": "Arrington XRP Capital",
    "portfolio": "Cred"
  },
  {
    "id": 67,
    "company_name": "Arrington XRP Capital",
    "portfolio": "NKN"
  },
  {
    "id": 68,
    "company_name": "Arrington XRP Capital",
    "portfolio": "Fantom"
  },
  {
    "id": 69,
    "company_name": "Arrington XRP Capital",
    "portfolio": "Sentinel Protocol"
  },
  {
    "id": 70,
    "company_name": "Arrington XRP Capital",
    "portfolio": "Sentinel"
  },
  {
    "id": 71,
    "company_name": "Arrington XRP Capital",
    "portfolio": "Carry"
  },
  {
    "id": 72,
    "company_name": "Arrington XRP Capital",
    "portfolio": "Aergo"
  },
  {
    "id": 73,
    "company_name": "Pithia",
    "portfolio": "RChain"
  },
  {
    "id": 74,
    "company_name": "#Hashed",
    "portfolio": "Ethereum"
  },
  {
    "id": 75,
    "company_name": "#Hashed",
    "portfolio": "Qtum"
  },
  {
    "id": 76,
    "company_name": "#Hashed",
    "portfolio": "EOS"
  },
  {
    "id": 77,
    "company_name": "#Hashed",
    "portfolio": "Decentraland"
  },
  {
    "id": 78,
    "company_name": "#Hashed",
    "portfolio": "StormX"
  },
  {
    "id": 79,
    "company_name": "#Hashed",
    "portfolio": "OST"
  },
  {
    "id": 80,
    "company_name": "#Hashed",
    "portfolio": "Kyber Network"
  },
  {
    "id": 81,
    "company_name": "#Hashed",
    "portfolio": "Red Pulse"
  },
  {
    "id": 82,
    "company_name": "#Hashed",
    "portfolio": "Airswap"
  },
  {
    "id": 83,
    "company_name": "#Hashed",
    "portfolio": "WAX"
  },
  {
    "id": 84,
    "company_name": "#Hashed",
    "portfolio": "Bluzelle"
  },
  {
    "id": 85,
    "company_name": "#Hashed",
    "portfolio": "Pundi X [new]"
  },
  {
    "id": 86,
    "company_name": "#Hashed",
    "portfolio": "aelf"
  },
  {
    "id": 87,
    "company_name": "#Hashed",
    "portfolio": "Loki"
  },
  {
    "id": 88,
    "company_name": "#Hashed",
    "portfolio": "BnkToTheFuture"
  },
  {
    "id": 89,
    "company_name": "#Hashed",
    "portfolio": "Zippie"
  },
  {
    "id": 90,
    "company_name": "#Hashed",
    "portfolio": "IoT Chain"
  },
  {
    "id": 91,
    "company_name": "#Hashed",
    "portfolio": "SureRemit"
  },
  {
    "id": 92,
    "company_name": "#Hashed",
    "portfolio": "TomoChain"
  },
  {
    "id": 93,
    "company_name": "#Hashed",
    "portfolio": "Ontology"
  },
  {
    "id": 94,
    "company_name": "#Hashed",
    "portfolio": "Refereum"
  },
  {
    "id": 95,
    "company_name": "#Hashed",
    "portfolio": "IoTeX"
  },
  {
    "id": 96,
    "company_name": "#Hashed",
    "portfolio": "traceto"
  },
  {
    "id": 97,
    "company_name": "#Hashed",
    "portfolio": "QuarkChain"
  },
  {
    "id": 98,
    "company_name": "#Hashed",
    "portfolio": "Internet Computer [IOU]"
  },
  {
    "id": 99,
    "company_name": "#Hashed",
    "portfolio": "MediBloc"
  },
  {
    "id": 100,
    "company_name": "#Hashed",
    "portfolio": "ICON"
  },
  {
    "id": 101,
    "company_name": "#Hashed",
    "portfolio": "Sentinel Protocol"
  },
  {
    "id": 102,
    "company_name": "#Hashed",
    "portfolio": "Cosmo Coin"
  },
  {
    "id": 103,
    "company_name": "#Hashed",
    "portfolio": "TTC"
  },
  {
    "id": 104,
    "company_name": "#Hashed",
    "portfolio": "Carry"
  },
  {
    "id": 105,
    "company_name": "#Hashed",
    "portfolio": "DarcMatter Coin"
  },
  {
    "id": 106,
    "company_name": "Huobi Global",
    "portfolio": "Huobi Pool Token"
  },
  {
    "id": 107,
    "company_name": "Huobi Global",
    "portfolio": "Huobi Token"
  },
  {
    "id": 108,
    "company_name": "Ethereum Foundation",
    "portfolio": "Ethereum"
  },
  {
    "id": 109,
    "company_name": "Ripple",
    "portfolio": "XRP"
  },
  {
    "id": 110,
    "company_name": "Binance",
    "portfolio": "Gifto"
  },
  {
    "id": 111,
    "company_name": "Binance",
    "portfolio": "Cred"
  },
  {
    "id": 112,
    "company_name": "ConsenSys",
    "portfolio": "Omega One"
  },
  {
    "id": 113,
    "company_name": "ConsenSys",
    "portfolio": "Gnosis"
  },
  {
    "id": 114,
    "company_name": "ConsenSys",
    "portfolio": "Grid+"
  },
  {
    "id": 115,
    "company_name": "ConsenSys",
    "portfolio": "Airswap"
  },
  {
    "id": 116,
    "company_name": "Three Arrows Capital",
    "portfolio": "Meta"
  },
  {
    "id": 117,
    "company_name": "Three Arrows Capital",
    "portfolio": "JOE"
  },
  {
    "id": 118,
    "company_name": "Three Arrows Capital",
    "portfolio": "Kyber Network"
  },
  {
    "id": 119,
    "company_name": "Three Arrows Capital",
    "portfolio": "Aave"
  },
  {
    "id": 120,
    "company_name": "Three Arrows Capital",
    "portfolio": "Terra"
  },
  {
    "id": 121,
    "company_name": "Three Arrows Capital",
    "portfolio": "Solana"
  },
  {
    "id": 122,
    "company_name": "Three Arrows Capital",
    "portfolio": "Polkadot"
  },
  {
    "id": 123,
    "company_name": "Three Arrows Capital",
    "portfolio": "NEAR Protocol"
  },
  {
    "id": 124,
    "company_name": "Three Arrows Capital",
    "portfolio": "Mina"
  },
  {
    "id": 125,
    "company_name": "Three Arrows Capital",
    "portfolio": "Kusama"
  },
  {
    "id": 126,
    "company_name": "Three Arrows Capital",
    "portfolio": "Ethereum"
  },
  {
    "id": 127,
    "company_name": "Three Arrows Capital",
    "portfolio": "Bitcoin"
  },
  {
    "id": 128,
    "company_name": "Paradigm",
    "portfolio": "PHANTOM"
  },
  {
    "id": 129,
    "company_name": "Paradigm",
    "portfolio": "Osmosis"
  },
  {
    "id": 130,
    "company_name": "Paradigm",
    "portfolio": "OpenSea"
  },
  {
    "id": 131,
    "company_name": "Paradigm",
    "portfolio": "Maker"
  },
  {
    "id": 132,
    "company_name": "Paradigm",
    "portfolio": "Keep Network"
  },
  {
    "id": 133,
    "company_name": "Paradigm",
    "portfolio": "Gitcoin"
  },
  {
    "id": 134,
    "company_name": "Paradigm",
    "portfolio": "FTX"
  },
  {
    "id": 135,
    "company_name": "Paradigm",
    "portfolio": "dYdX"
  },
  {
    "id": 136,
    "company_name": "Paradigm",
    "portfolio": "Cosmos"
  },
  {
    "id": 137,
    "company_name": "Paradigm",
    "portfolio": "Compound"
  },
  {
    "id": 138,
    "company_name": "Paradigm",
    "portfolio": "Coinbase"
  },
  {
    "id": 139,
    "company_name": "Paradigm",
    "portfolio": "Citadel"
  },
  {
    "id": 140,
    "company_name": "Paradigm",
    "portfolio": "Chainalysis"
  },
  {
    "id": 141,
    "company_name": "Paradigm",
    "portfolio": "BlockFi"
  },
  {
    "id": 142,
    "company_name": "GhostRider Ventures",
    "portfolio": "Olympus"
  },
  {
    "id": 143,
    "company_name": "GhostRider Ventures",
    "portfolio": "Avalanche"
  },
  {
    "id": 144,
    "company_name": "GhostRider Ventures",
    "portfolio": "Solana"
  },
  {
    "id": 145,
    "company_name": "GhostRider Ventures",
    "portfolio": "Fantom"
  },
  {
    "id": 146,
    "company_name": "GhostRider Ventures",
    "portfolio": "The Sandbox"
  },
  {
    "id": 147,
    "company_name": "GhostRider Ventures",
    "portfolio": "Terra"
  },
  {
    "id": 148,
    "company_name": "GhostRider Ventures",
    "portfolio": "Kusama"
  },
  {
    "id": 149,
    "company_name": "GhostRider Ventures",
    "portfolio": "Polkadot"
  },
  {
    "id": 150,
    "company_name": "Input Output",
    "portfolio": "Ethereum Classic"
  },
  {
    "id": 151,
    "company_name": "Input Output",
    "portfolio": "Cardano"
  },
  {
    "id": 152,
    "company_name": "Ava Labs",
    "portfolio": "Avalanche"
  },
  {
    "id": 153,
    "company_name": "Ascensive Assets",
    "portfolio": "SolRazr"
  },
  {
    "id": 154,
    "company_name": "Jsquare",
    "portfolio": "RMRK"
  },
  {
    "id": 155,
    "company_name": "Jsquare",
    "portfolio": "Efinity Token"
  },
  {
    "id": 156,
    "company_name": "Reflexer Labs",
    "portfolio": "Rai Reflex Index"
  },
  {
    "id": 157,
    "company_name": "Reflexer Labs",
    "portfolio": "Reflexer Ungovernance Token"
  },
  {
    "id": 158,
    "company_name": "Sky Mavis",
    "portfolio": "Ronin Wallet"
  },
  {
    "id": 159,
    "company_name": "Sky Mavis",
    "portfolio": "Small Love Potion"
  },
  {
    "id": 160,
    "company_name": "Sky Mavis",
    "portfolio": "Axie Infinity"
  },
  {
    "id": 161,
    "company_name": "Digital Finance Group",
    "portfolio": "Ripio Credit Network"
  },
  {
    "id": 162,
    "company_name": "Digital Finance Group",
    "portfolio": "Circle"
  },
  {
    "id": 163,
    "company_name": "Digital Finance Group",
    "portfolio": "Brave Browser"
  },
  {
    "id": 164,
    "company_name": "Digital Finance Group",
    "portfolio": "Exchange Union"
  },
  {
    "id": 165,
    "company_name": "Digital Finance Group",
    "portfolio": "Matrix AI Network"
  },
  {
    "id": 166,
    "company_name": "Digital Finance Group",
    "portfolio": "Polkadot"
  },
  {
    "id": 167,
    "company_name": "DeFiance Capital",
    "portfolio": "BoringDAO"
  },
  {
    "id": 168,
    "company_name": "DeFiance Capital",
    "portfolio": "ParaSwap"
  },
  {
    "id": 169,
    "company_name": "DeFiance Capital",
    "portfolio": "Balancer"
  },
  {
    "id": 170,
    "company_name": "DeFiance Capital",
    "portfolio": "mStable"
  },
  {
    "id": 171,
    "company_name": "DeFiance Capital",
    "portfolio": "Bancor"
  },
  {
    "id": 172,
    "company_name": "DeFiance Capital",
    "portfolio": "DODO"
  },
  {
    "id": 173,
    "company_name": "DeFiance Capital",
    "portfolio": "JOE"
  },
  {
    "id": 174,
    "company_name": "DeFiance Capital",
    "portfolio": "Lido DAO Token"
  },
  {
    "id": 175,
    "company_name": "DeFiance Capital",
    "portfolio": "Aave"
  },
  {
    "id": 176,
    "company_name": "DeFiance Capital",
    "portfolio": "dYdX"
  },
  {
    "id": 177,
    "company_name": "Terraform Labs",
    "portfolio": "TerraKRW"
  },
  {
    "id": 178,
    "company_name": "Terraform Labs",
    "portfolio": "Mirror Protocol"
  },
  {
    "id": 179,
    "company_name": "Terraform Labs",
    "portfolio": "TerraUSD"
  },
  {
    "id": 180,
    "company_name": "Terraform Labs",
    "portfolio": "Terra"
  },
  {
    "id": 181,
    "company_name": "Coinbase Ventures",
    "portfolio": "TaxBit"
  },
  {
    "id": 182,
    "company_name": "Coinbase Ventures",
    "portfolio": "Flow (Dapper Labs)"
  },
  {
    "id": 183,
    "company_name": "Coinbase Ventures",
    "portfolio": "Immutable X"
  },
  {
    "id": 184,
    "company_name": "Coinbase Ventures",
    "portfolio": "iBTC (Synthetix)"
  },
  {
    "id": 185,
    "company_name": "Coinbase Ventures",
    "portfolio": "BlockFi"
  },
  {
    "id": 186,
    "company_name": "Coinbase Ventures",
    "portfolio": "Compound"
  },
  {
    "id": 187,
    "company_name": "Alameda Research",
    "portfolio": "Immutable X"
  },
  {
    "id": 188,
    "company_name": "Animoca Brands",
    "portfolio": "Bondly"
  },
  {
    "id": 189,
    "company_name": "Animoca Brands",
    "portfolio": "REVV"
  },
  {
    "id": 190,
    "company_name": "Animoca Brands",
    "portfolio": "The Sandbox"
  },
  {
    "id": 191,
    "company_name": "Union Square Ventures",
    "portfolio": "Coinbase"
  },
  {
    "id": 192,
    "company_name": "Union Square Ventures",
    "portfolio": "Algorand"
  },
  {
    "id": 193,
    "company_name": "Union Square Ventures",
    "portfolio": "Arweave"
  },
  {
    "id": 194,
    "company_name": "Union Square Ventures",
    "portfolio": "Polygon"
  },
  {
    "id": 195,
    "company_name": "Dapper Labs",
    "portfolio": "Flow (Dapper Labs)"
  },
  {
    "id": 196,
    "company_name": "Blockchain Game Alliance",
    "portfolio": "Tezos"
  },
  {
    "id": 197,
    "company_name": "Blockchain Game Alliance",
    "portfolio": "My DeFi Pet"
  },
  {
    "id": 198,
    "company_name": "Blockchain Game Alliance",
    "portfolio": "Sensorium"
  },
  {
    "id": 199,
    "company_name": "Blockchain Game Alliance",
    "portfolio": "Seedify.fund"
  },
  {
    "id": 200,
    "company_name": "Blockchain Game Alliance",
    "portfolio": "Crypto Briefing"
  },
  {
    "id": 201,
    "company_name": "Blockchain Game Alliance",
    "portfolio": "Bondly"
  },
  {
    "id": 202,
    "company_name": "Blockchain Game Alliance",
    "portfolio": "Avalanche"
  },
  {
    "id": 203,
    "company_name": "Blockchain Game Alliance",
    "portfolio": "Gala"
  },
  {
    "id": 204,
    "company_name": "Blockchain Game Alliance",
    "portfolio": "CUDOS"
  },
  {
    "id": 205,
    "company_name": "Blockchain Game Alliance",
    "portfolio": "OpenSea"
  },
  {
    "id": 206,
    "company_name": "Blockchain Game Alliance",
    "portfolio": "MetaMask"
  },
  {
    "id": 207,
    "company_name": "Blockchain Game Alliance",
    "portfolio": "Sky Mavis"
  },
  {
    "id": 208,
    "company_name": "Blockchain Game Alliance",
    "portfolio": "Ultra"
  },
  {
    "id": 209,
    "company_name": "Blockchain Game Alliance",
    "portfolio": "The Sandbox"
  },
  {
    "id": 210,
    "company_name": "Blockchain Game Alliance",
    "portfolio": "Enjin Coin"
  }
]
